{"bookings":{"S1_20_0":["mehaseeb","poornah","chaakast","bhulekgu"],"S1_20_15":["mehaseeb","poornah","chaakast","bhulekgu"],"S1_18_45":["mehaseeb","urdivya","bbabitaj","vtsandhy"],"S1_18_0":["poornah"],"S1_18_30":["urdivya","bbabitaj","shravyal"],"S1_14_45":["mehaseeb","schetanc"],"S1_17_15":["urdivya"],"S1_17_0":["bbabitaj"],"S1_13_30":["shravyal"],"S1_15_0":["schetanc"]},"history":[{"user":"mehaseeb","slotLabel":"8:00 PM - 8:15 PM","bookedAt":"5/7/2026, 3:45:01 pm"},{"user":"mehaseeb","slotLabel":"8:15 PM - 8:30 PM","bookedAt":"5/7/2026, 3:45:02 pm"},{"user":"mehaseeb","slotLabel":"6:45 PM - 7:00 PM","bookedAt":"5/7/2026, 3:45:09 pm"},{"user":"poornah","slotLabel":"8:00 PM - 8:15 PM","bookedAt":"5/7/2026, 3:45:17 pm"},{"user":"poornah","slotLabel":"8:15 PM - 8:30 PM","bookedAt":"5/7/2026, 3:45:19 pm"},{"user":"poornah","slotLabel":"6:00 PM - 6:15 PM","bookedAt":"5/7/2026, 3:45:22 pm"},{"user":"chaakast","slotLabel":"8:15 PM - 8:30 PM","bookedAt":"5/7/2026, 3:45:30 pm"},{"user":"chaakast","slotLabel":"8:00 PM - 8:15 PM","bookedAt":"5/7/2026, 3:45:32 pm"},{"user":"urdivya","slotLabel":"6:30 PM - 6:45 PM","bookedAt":"5/7/2026, 3:45:39 pm"},{"user":"urdivya","slotLabel":"6:45 PM - 7:00 PM","bookedAt":"5/7/2026, 3:45:44 pm"},{"user":"mehaseeb","slotLabel":"2:45 PM - 3:00 PM","bookedAt":"5/7/2026, 3:45:52 pm"},{"user":"urdivya","slotLabel":"5:15 PM - 5:30 PM","bookedAt":"5/7/2026, 3:46:03 pm"},{"user":"bbabitaj","slotLabel":"6:30 PM - 6:45 PM","bookedAt":"5/7/2026, 3:47:00 pm"},{"user":"bbabitaj","slotLabel":"6:45 PM - 7:00 PM","bookedAt":"5/7/2026, 3:47:01 pm"},{"user":"bhulekgu","slotLabel":"8:00 PM - 8:15 PM","bookedAt":"5/7/2026, 3:47:59 pm"},{"user":"bhulekgu","slotLabel":"8:15 PM - 8:30 PM","bookedAt":"5/7/2026, 3:48:00 pm"},{"user":"bbabitaj","slotLabel":"5:00 PM - 5:15 PM","bookedAt":"5/7/2026, 3:48:52 pm"},{"user":"vtsandhy","slotLabel":"6:45 PM - 7:00 PM","bookedAt":"5/7/2026, 3:54:27 pm"},{"user":"shravyal","slotLabel":"1:30 PM - 1:45 PM","bookedAt":"5/7/2026, 3:58:33 pm"},{"user":"shravyal","slotLabel":"6:30 PM - 6:45 PM","bookedAt":"5/7/2026, 3:58:39 pm"},{"user":"schetanc","slotLabel":"2:45 PM - 3:00 PM","bookedAt":"5/7/2026, 4:04:05 pm"},{"user":"schetanc","slotLabel":"3:00 PM - 3:15 PM","bookedAt":"5/7/2026, 4:04:05 pm"}]}